<?xml version="1.0" encoding="UTF-8"?>
<mappings xmlns="http://dozer.sourceforge.net"
	xmlns:xsi="http://www.w3.org/2001/XMLSchema-instance"
	xsi:schemaLocation="http://dozer.sourceforge.net
	http://dozer.sourceforge.net/schema/beanmapping.xsd">
	
	<mapping map-id="dataQuery.po2vo" >
		<class-a>com.netsteadfast.greenstep.po.hbm.QcDataQuery</class-a>
		<class-b>com.netsteadfast.greenstep.vo.DataQueryVO</class-b>
		<field>
			<a>oid</a>
			<b>oid</b>
		</field>
		<field>
			<a>name</a>
			<b>name</b>
		</field>	
		<field>
			<a>conf</a>
			<b>conf</b>
		</field>
		<field>
			<a>queryExpression</a>
			<b>queryExpression</b>
		</field>	
		<field>
			<a>mapperOid</a>
			<b>mapperOid</b>
		</field>												
	</mapping>

	<mapping map-id="dataQuery.vo2po" >
		<class-a>com.netsteadfast.greenstep.vo.DataQueryVO</class-a>
		<class-b>com.netsteadfast.greenstep.po.hbm.QcDataQuery</class-b>
		<field>
			<a>oid</a>
			<b>oid</b>
		</field>
		<field>
			<a>name</a>
			<b>name</b>
		</field>	
		<field>
			<a>conf</a>
			<b>conf</b>
		</field>
		<field>
			<a>queryExpression</a>
			<b>queryExpression</b>
		</field>	
		<field>
			<a>mapperOid</a>
			<b>mapperOid</b>
		</field>			
	</mapping>
	
</mappings>
