<?xml version="1.0" encoding="UTF-8"?>
<mappings xmlns="http://dozer.sourceforge.net"
	xmlns:xsi="http://www.w3.org/2001/XMLSchema-instance"
	xsi:schemaLocation="http://dozer.sourceforge.net
	http://dozer.sourceforge.net/schema/beanmapping.xsd">
	
	<mapping map-id="kpi.po2vo" >
		<class-a>com.netsteadfast.greenstep.po.hbm.BbKpi</class-a>
		<class-b>com.netsteadfast.greenstep.vo.KpiVO</class-b>
		<field>
			<a>oid</a>
			<b>oid</b>
		</field>
		<field>
			<a>id</a>
			<b>id</b>
		</field>
		<field>
			<a>objId</a>
			<b>objId</b>
		</field>
		<field>
			<a>name</a>
			<b>name</b>
		</field>	
		<field>
			<a>description</a>
			<b>description</b>
		</field>	
		<field>
			<a>weight</a>
			<b>weight</b>
		</field>	
		<field>
			<a>unit</a>
			<b>unit</b>
		</field>		
		<field>
			<a>forId</a>
			<b>forId</b>
		</field>
		<field>
			<a>trendsForId</a>
			<b>trendsForId</b>
		</field>				
		<field>
			<a>max</a>
			<b>max</b>
		</field>			
		<field>
			<a>target</a>
			<b>target</b>
		</field>
		<field>
			<a>min</a>
			<b>min</b>
		</field>	
		<field>
			<a>management</a>
			<b>management</b>
		</field>	
		<field>
			<a>compareType</a>
			<b>compareType</b>
		</field>
		<field>
			<a>cal</a>
			<b>cal</b>
		</field>
		<field>
			<a>dataType</a>
			<b>dataType</b>
		</field>
		<field>
			<a>orgaMeasureSeparate</a>
			<b>orgaMeasureSeparate</b>
		</field>
		<field>
			<a>userMeasureSeparate</a>
			<b>userMeasureSeparate</b>
		</field>		
		<field>
			<a>quasiRange</a>
			<b>quasiRange</b>
		</field>
		<field>
			<a>activate</a>
			<b>activate</b>
		</field>																																							
	</mapping>

	<mapping map-id="kpi.vo2po" >
		<class-a>com.netsteadfast.greenstep.vo.KpiVO</class-a>
		<class-b>com.netsteadfast.greenstep.po.hbm.BbKpi</class-b>
		<field>
			<a>oid</a>
			<b>oid</b>
		</field>
		<field>
			<a>id</a>
			<b>id</b>
		</field>
		<field>
			<a>objId</a>
			<b>objId</b>
		</field>
		<field>
			<a>name</a>
			<b>name</b>
		</field>	
		<field>
			<a>description</a>
			<b>description</b>
		</field>	
		<field>
			<a>weight</a>
			<b>weight</b>
		</field>	
		<field>
			<a>unit</a>
			<b>unit</b>
		</field>	
		<field>
			<a>forId</a>
			<b>forId</b>
		</field>
		<field>
			<a>trendsForId</a>
			<b>trendsForId</b>
		</field>		
		<field>
			<a>max</a>
			<b>max</b>
		</field>			
		<field>
			<a>target</a>
			<b>target</b>
		</field>
		<field>
			<a>min</a>
			<b>min</b>
		</field>	
		<field>
			<a>management</a>
			<b>management</b>
		</field>	
		<field>
			<a>compareType</a>
			<b>compareType</b>
		</field>
		<field>
			<a>cal</a>
			<b>cal</b>
		</field>
		<field>
			<a>dataType</a>
			<b>dataType</b>
		</field>
		<field>
			<a>orgaMeasureSeparate</a>
			<b>orgaMeasureSeparate</b>
		</field>
		<field>
			<a>userMeasureSeparate</a>
			<b>userMeasureSeparate</b>
		</field>	
		<field>
			<a>quasiRange</a>
			<b>quasiRange</b>
		</field>	
		<field>
			<a>activate</a>
			<b>activate</b>
		</field>					
	</mapping>
	
</mappings>
